CHANGES.txt
LICENSE.txt
MANIFEST.in
README.rst
requirements.txt
setup.py
agrimpy/__init__.py
agrimpy/geod_proy.py
agrimpy/gms_gyf.py
agrimpy/test.py
agrimpy/toDXF.py
agrimpy.egg-info/PKG-INFO
agrimpy.egg-info/SOURCES.txt
agrimpy.egg-info/dependency_links.txt
agrimpy.egg-info/requires.txt
agrimpy.egg-info/top_level.txt
agrimpy/coord/proy
agrimpy/coord/proy.dxf
agrimpy/coord/proy.geod
agrimpy/coord/proy.geod.gk5
agrimpy/coord/proy.geod.gk5.dxf
agrimpy/coord/proy.geod.gk5.geod
agrimpy/coord/proy.geod.gk5.geod.gk5
agrimpy/coord/proy.geod.gk5.geod.gk5.dxf
agrimpy/coord/proy.geod.gk5.geod.gk5.geod
agrimpy/coord/proy.geod.proy
agrimpy/coord/proy.geod.proy.dxf
agrimpy/coord/proy.geod.proy.geod