Metadata-Version: 1.0
Name: agrimpy
Version: 0.0.6
Summary: Algunas operaciones con coordenadas geodésicas.
Home-page: http://pypi.python.org/pypi/agrimpy/
Author: Santiago Pestarini
Author-email: santiago@pestarini.com.ar
License: LICENSE.txt
Platform: UNKNOWN
